flowsy/__init__.py
flowsy/_nbdev.py
flowsy/core.py
flowsy/pre.py
flowsy/train.py
flowsy-0.0.6.dist-info/LICENSE
flowsy-0.0.6.dist-info/METADATA
flowsy-0.0.6.dist-info/WHEEL
flowsy-0.0.6.dist-info/entry_points.txt
flowsy-0.0.6.dist-info/top_level.txt
flowsy-0.0.6.dist-info/RECORD
