Metadata-Version: 2.1
Name: flowsy
Version: 0.0.6
Summary: A simple way to get recommendations
Home-page: https://github.com/daniel-riffi/flowsy/tree/master/
Author: Daniel Riffert
Author-email: riffert.daniel@gmail.com
License: Apache Software License 2.0
Keywords: fast.ai nbdev
Platform: UNKNOWN
Classifier: Development Status :: 3 - Alpha
Classifier: Intended Audience :: Developers
Classifier: License :: OSI Approved :: Apache Software License
Classifier: Natural Language :: English
Classifier: Programming Language :: Python :: 3.6
Classifier: Programming Language :: Python :: 3.7
Classifier: Programming Language :: Python :: 3.8
Requires-Python: >=3.6
Requires-Dist: fastai
